morselate/__init__.py
morselate/__main__.py
morselate/morselate.py
morselate-0.0.1.dist-info/DESCRIPTION.rst
morselate-0.0.1.dist-info/METADATA
morselate-0.0.1.dist-info/RECORD
morselate-0.0.1.dist-info/WHEEL
morselate-0.0.1.dist-info/metadata.json
morselate-0.0.1.dist-info/top_level.txt
