Metadata-Version: 2.0
Name: morselate
Version: 0.0.1
Summary: Yet another morse encoder/decoder
Home-page: https://github.com/SamambaMan/morselate
Author: Felipe Ferreira
Author-email: felipe.gomes.ferreira@gmail.com
License: BSD
Keywords: morsecode morse
Platform: UNKNOWN
Classifier: Development Status :: 3 - Alpha
Classifier: Topic :: Utilities
Classifier: License :: OSI Approved :: BSD License
